abiflows/__init__.py
abiflows/core/__init__.py
abiflows/core/controllers.py
abiflows/core/mastermind_abc.py
abiflows/core/models.py
abiflows/core/release.py
abiflows/core/testing.py
abiflows/core/tests/__init__.py
abiflows/core/tests/test_cleaner.py
abiflows/database/__init__.py
abiflows/database/mongoengine/__init__.py
abiflows/database/mongoengine/abinit_mixins.py
abiflows/database/mongoengine/abinit_results.py
abiflows/database/mongoengine/mixins.py
abiflows/database/mongoengine/utils.py
abiflows/database/mongoengine/tests/__init__.py
abiflows/database/mongoengine/tests/test_abinit_mixins.py
abiflows/database/mongoengine/tests/test_abinit_results.py
abiflows/database/mongoengine/tests/test_mixins.py
abiflows/database/mongoengine/tests/test_utils.py
abiflows/fireworks/__init__.py
abiflows/fireworks/examples/__init__.py
abiflows/fireworks/examples/phonon_wf.py
abiflows/fireworks/examples/relax_wf.py
abiflows/fireworks/integration_tests/__init__.py
abiflows/fireworks/integration_tests/conftest.py
abiflows/fireworks/integration_tests/itest_check_abiflow.py
abiflows/fireworks/integration_tests/itest_dfpt.py
abiflows/fireworks/integration_tests/itest_dte.py
abiflows/fireworks/integration_tests/itest_nscf.py
abiflows/fireworks/integration_tests/itest_phonon.py
abiflows/fireworks/integration_tests/itest_relax.py
abiflows/fireworks/integration_tests/itest_scf.py
abiflows/fireworks/tasks/__init__.py
abiflows/fireworks/tasks/abinit_common.py
abiflows/fireworks/tasks/abinit_tasks.py
abiflows/fireworks/tasks/abinit_tasks_src.py
abiflows/fireworks/tasks/analysis_tasks.py
abiflows/fireworks/tasks/flow_wrapper_tasks.py
abiflows/fireworks/tasks/handlers.py
abiflows/fireworks/tasks/n1000multiples_primes.json
abiflows/fireworks/tasks/src_tasks_abc.py
abiflows/fireworks/tasks/utility_tasks.py
abiflows/fireworks/tasks/vasp_sets.py
abiflows/fireworks/tasks/vasp_tasks_src.py
abiflows/fireworks/tasks/tests/__init__.py
abiflows/fireworks/tasks/tests/mock_objects.py
abiflows-0.6.dist-info/LICENSE
abiflows-0.6.dist-info/METADATA
abiflows-0.6.dist-info/WHEEL
abiflows-0.6.dist-info/top_level.txt
abiflows-0.6.dist-info/RECORD
