Metadata-Version: 2.1
Name: abiflows
Version: 0.6
Summary: Framework for high-throughput calculations with ABINIT
Home-page: https://github.com/abinit/abiflows
Author: The Abinit group
Author-email: matteo.giantomassi@uclouvain.be
License: GPL
Keywords: ABINIT,ab-initio,density-function-theory,first-principles,electronic-structure,pymatgen
Platform: Linux
Platform: darwin
Classifier: Programming Language :: Python :: 3
Classifier: Programming Language :: Python :: 3.6
Classifier: Programming Language :: Python :: 3.7
Classifier: Development Status :: 4 - Beta
Classifier: Intended Audience :: Science/Research
Classifier: License :: OSI Approved :: GNU General Public License v2 (GPLv2)
Classifier: Operating System :: OS Independent
Classifier: Topic :: Scientific/Engineering :: Information Analysis
Classifier: Topic :: Scientific/Engineering :: Physics
Classifier: Topic :: Scientific/Engineering :: Chemistry
Classifier: Topic :: Software Development :: Libraries :: Python Modules
Requires-Dist: six
Requires-Dist: numpy
Requires-Dist: pymongo
Requires-Dist: prettytable
Requires-Dist: mongoengine
Requires-Dist: paramiko
Requires-Dist: custodian
Requires-Dist: fireworks
Requires-Dist: abipy (>=0.7.0)
